Workbook

Sheet Contents
A1: This file presents the data from the figures in CBO’s January 2026 report The Distribution of Household Income, 2022.
A2: www.cbo.gov/publication/61911
A5: Contents
A7: ='Figure 1'!A5 -> Figure 1. Average Income, Means-Tested Transfers, and Federal Taxes in 2022
A8: ='Figure 2'!A5 -> Figure 2. Cumulative Growth in Average Household Income Before Transfers and Taxes, 2019 to 2022
A9: ='Figure 3'!A5 -> Figure 3. Cumulative Growth in Average Household Income After Transfers and Taxes, 2019 to 2022
A10: ='Figure 4'!A5 -> Figure 4. Average Income Before Transfers and Taxes, 2019 to 2022
A11: ='Figure 5'!A5 -> Figure 5. Average Income Before Transfers and Taxes and Its Growth, 1979 to 2022
A12: ='Figure 6'!A5 -> Exhibit 6. Cumulative Growth in Average Income Before Transfers and Taxes for Households in the Highest Quintile, 1979 to 2022
A13: ='Figure 7'!A5 -> Figure 7. Composition of Income Before Transfers and Taxes for Households in the Top 1 Percent, 1979 to 2022
A14: ='Figure 8'!A5 -> Figure 8. Income Groups’ Shares of Income Before Transfers and Taxes, 1979 to 2022
A15: ='Figure 9'!A5 -> Figure 9. Average Means-Tested Transfer Rates for Selected Income Groups, 1979 to 2022
A16: ='Figure 10'!A5 -> Figure 10. Average Means-Tested Transfer Rates for Households in the Lowest Quintile, by Type of Transfer, 1979 to 2022
A17: ='Figure 11'!A5 -> Figure 11. Average Federal Tax Rates, 1979 to 2022
A18: ='Figure 12'!A5 -> Figure 12. Average Federal Tax Rates for Households in the Top 1 Percent, 1979 to 2022
A19: ='Figure 13'!A5 -> Figure 13. Average Federal Tax Rates, by Type of Tax, 1979 to 2022
A20: ='Figure 14'!A5 -> Figure 14. Average Federal Tax Rates, by Type of Tax and Income Group, 1979 to 2022
A21: ='Figure 15'!A5 -> Figure 15. Average Refundable Credits Measured as a Percentage of Income Before Transfers and Taxes for Selected Income Groups, 1979 to 2022
A22: ='Figure 16'!A5 -> Figure 16. Income Groups’ Shares of Federal Taxes, 1979 to 2022
A23: ='Figure 17'!A5 -> Figure 17. Average Income After Transfers and Taxes, 2019 to 2022
A24: ='Figure 18'!A5 -> Figure 18. Average Income After Transfers and Taxes and Its Growth, 1979 to 2022
A25: ='Figure 19'!A5 -> Figure 19. Cumulative Growth in Average Income After Transfers and Taxes for Households in the Highest Quintile, 1979 to 2022
A26: ='Figure 20'!A5 -> Figure 20. Income Groups’ Shares of Income After Transfers and Taxes, 1979 to 2022
A27: ='Figure 21'!A5 -> Figure 21. Income Inequality, as Measured by the Gini Coefficient, 1979 to 2022
A28: ='Figure 22'!A5 -> Figure 22. Reduction in Income Inequality Stemming From Means-Tested Transfers and Federal Taxes, 1979 to 2022

Sheet Figure 1
A1: This file presents the data from the figures in CBO’s January 2026 report The Distribution of Household Income, 2022.
A2: www.cbo.gov/publication/61911
A5: Figure 1. Average Income, Means-Tested Transfers, and Federal Taxes in 2022
A6: Thousands of 2022 dollars
B8: Income before transfers and taxes | C8: Means-tested transfers | D8: Federal taxes | E8: Income after transfers and taxes
A9: Lowest quintile | B9: 26.238 | C9: 18.973 | D9: 0.373 | E9: 44.838
A10: Second quintile | B10: 59.146 | C10: 9.597 | D10: 5.604 | E10: 63.138
A11: Third quintile | B11: 93.992 | C11: 5.621 | D11: 12.617 | E11: 86.997
A12: Fourth quintile | B12: 143.147 | C12: 3.039 | D12: 25.134 | E12: 121.052
A13: Highest quintile | B13: 412.628 | C13: 1.701 | D13: 106.68 | E13: 307.649
A16: Back to Table of Contents

Sheet Figure 2
A1: This file presents the data from the figures in CBO’s January 2026 report The Distribution of Household Income, 2022.
A2: www.cbo.gov/publication/61911
A5: Figure 2. Cumulative Growth in Average Household Income Before Transfers and Taxes, 2019 to 2022
A6: Percent
B8: 2020 | C8: 2021 | D8: 2022
A9: Lowest quintile | B9: -9.623 | C9: -8.73 | D9: -2.272
A10: Middle three quintiles | B10: -0.165 | C10: 0.254 | D10: 1.739
A11: Highest quintile | B11: 6.223 | C11: 19.071 | D11: 10.276
A14: Back to Table of Contents

Sheet Figure 3
A1: This file presents the data from the figures in CBO’s January 2026 report The Distribution of Household Income, 2022.
A2: www.cbo.gov/publication/61911
A5: Figure 3. Cumulative Growth in Average Household Income After Transfers and Taxes, 2019 to 2022
A6: Percent
B8: 2019 | C8: 2020 | D8: 2021 | E8: 2022
A9: Lowest quintile | B9: 0 | C9: 14.911 | D9: 17.16 | E9: 1.62
A10: Middle three quintiles | B10: 0 | C10: 9.604 | D10: 8.371 | E10: 2.189
A11: Highest quintile | B11: 0 | C11: 7.494 | D11: 18.787 | E11: 8.171
A14: Back to Table of Contents

Sheet Figure 4
A1: This file presents the data from the figures in CBO’s January 2026 report The Distribution of Household Income, 2022.
A2: www.cbo.gov/publication/61911
A5: Figure 4. Average Income Before Transfers and Taxes, 2019 to 2022
A6: Thousands of 2022 dollars
B8: 2019 | C8: 2020 | D8: 2021 | E8: =D8+1 -> 2022
A9: Lowest quintile | B9: 26.848 | C9: 24.264 | D9: 24.504 | E9: 26.238
A10: Second quintile | B10: 59.152 | C10: 57.394 | D10: 57.65 | E10: 59.146
A11: Middle quintile | B11: 92.187 | C11: 92.462 | D11: 92.637 | E11: 93.992
A12: Fourth quintile | B12: 138.797 | C12: 141.119 | D12: 141.585 | E12: 143.147
A13: Highest quintile | B13: 374.177 | C13: 397.463 | D13: 445.534 | E13: 412.628
A16: Back to Table of Contents

Sheet Figure 5
A1: This file presents the data from the figures in CBO’s January 2026 report The Distribution of Household Income, 2022.
A2: www.cbo.gov/publication/61911
A5: Figure 5. Average Income Before Transfers and Taxes and Its Growth, 1979 to 2022
B7: Average income (thousands of 2022 dollars) | F7: Cumulative growth (percent)
B8: Lowest quintile | C8: Middle three quintiles | D8: Highest quintile | F8: Lowest quintile | G8: Middle three quintiles | H8: Highest quintile
A9: 1979 | B9: 18.2 | C9: 67 | D9: 173 | F9: 0 | G9: 0 | H9: 0
A10: 1980 | B10: 17.5 | C10: 64.9 | D10: 168.4 | F10: -4 | G10: -3 | H10: -3
A11: 1981 | B11: 17.3 | C11: 64.9 | D11: 167.8 | F11: -5 | G11: -3 | H11: -3
A12: 1982 | B12: 16.7 | C12: 64.1 | D12: 169 | F12: -8 | G12: -4 | H12: -2
A13: 1983 | B13: 16 | C13: 63.4 | D13: 175.1 | F13: -12 | G13: -5 | H13: 1
A14: 1984 | B14: 17.2 | C14: 67 | D14: 189.9 | F14: -6 | G14: 0 | H14: 10
A15: 1985 | B15: 17.1 | C15: 67.2 | D15: 192.2 | F15: -6 | G15: 0 | H15: 11
A16: 1986 | B16: 17 | C16: 68.8 | D16: 215.8 | F16: -7 | G16: 3 | H16: 25
A17: 1987 | B17: 16.3 | C17: 68.3 | D17: 204.3 | F17: -11 | G17: 2 | H17: 18
A18: 1988 | B18: 16.9 | C18: 69.2 | D18: 218.6 | F18: -7 | G18: 3 | H18: 26
A19: 1989 | B19: 17.6 | C19: 69.9 | D19: 217.9 | F19: -3 | G19: 4 | H19: 26
A20: 1990 | B20: 18.2 | C20: 70.5 | D20: 212.6 | F20: 0 | G20: 5 | H20: 23
... A52: 2022 | B52: 26.2 | C52: 98.3 | D52: 412.6 | F52: 44 | G52: 47 | H52: 138
A55: Back to Table of Contents

Sheet Figure 6
A1: This file presents the data from the figures in CBO’s January 2026 report The Distribution of Household Income, 2022.
A2: www.cbo.gov/publication/61911
A5: Exhibit 6. Cumulative Growth in Average Income Before Transfers and Taxes for Households in the Highest Quintile, 1979 to 2022
A6: Percent
B8: 81st to 99th percentiles | C8: 99th to 99.9th percentiles | D8: 99.9th to 99.99th percentiles | E8: Top 0.01 percent
A9: 1979 | B9: 0 | C9: 0 | D9: 0 | E9: 0
A10: 1980 | B10: -2 | C10: -2 | D10: 2 | E10: -11
A11: 1981 | B11: -3 | C11: -4 | D11: 0 | E11: -14
A12: 1982 | B12: -3 | C12: -3 | D12: 12 | E12: 13
A13: 1983 | B13: -1 | C13: 6 | D13: 25 | E13: 16
A14: 1984 | B14: 6 | C14: 14 | D14: 40 | E14: 40
A15: 1985 | B15: 6 | C15: 22 | D15: 48 | E15: 50
A16: 1986 | B16: 13 | C16: 46 | D16: 133 | E16: 144
A17: 1987 | B17: 14 | C17: 31 | D17: 57 | E17: 42
A18: 1988 | B18: 16 | C18: 51 | D18: 104 | E18: 110
A19: 1989 | B19: 18 | C19: 46 | D19: 83 | E19: 84
A20: 1990 | B20: 16 | C20: 43 | D20: 76 | E20: 75
... A52: 2022 | B52: 102 | C52: 221 | D52: 442 | E52: 537
A55: Back to Table of Contents

Sheet Figure 7
A1: This file presents the data from the figures in CBO’s January 2026 report The Distribution of Household Income, 2022.
A2: www.cbo.gov/publication/61911
A5: Figure 7. Composition of Income Before Transfers and Taxes for Households in the Top 1 Percent, 1979 to 2022
A6: Millions of 2022 dollars
A8: Year | B8: Capital income, including capital gains | C8: Labor income | D8: Business income | E8: Social insurance benefits and other market income | F8: Total
A9: 1979 | B9: 0.362 | C9: 0.214 | D9: 0.07 | E9: 0.019 | F9: 0.665
A10: 1980 | B10: 0.335 | C10: 0.225 | D10: 0.059 | E10: 0.019 | F10: 0.638
A11: 1981 | B11: 0.345 | C11: 0.226 | D11: 0.044 | E11: 0.02 | F11: 0.635
A12: 1982 | B12: 0.361 | C12: 0.235 | D12: 0.051 | E12: 0.023 | F12: 0.669
A13: 1983 | B13: 0.398 | C13: 0.25 | D13: 0.061 | E13: 0.025 | F13: 0.733
A14: 1984 | B14: 0.442 | C14: 0.267 | D14: 0.075 | E14: 0.029 | F14: 0.813
A15: 1985 | B15: 0.492 | C15: 0.265 | D15: 0.078 | E15: 0.032 | F15: 0.868
A16: 1986 | B16: 0.775 | C16: 0.261 | D16: 0.076 | E16: 0.025 | F16: 1.136
A17: 1987 | B17: 0.427 | C17: 0.342 | D17: 0.116 | E17: 0.027 | F17: 0.912
A18: 1988 | B18: 0.506 | C18: 0.416 | D18: 0.173 | E18: 0.046 | F18: 1.141
A19: 1989 | B19: 0.478 | C19: 0.376 | D19: 0.168 | E19: 0.041 | F19: 1.063
A20: 1990 | B20: 0.42 | C20: 0.393 | D20: 0.171 | E20: 0.043 | F20: 1.028
... A52: 2022 | B52: 1.163 | C52: 0.776 | D52: 0.659 | E52: 0.103 | F52: 2.701
A55: Back to Table of Contents

Sheet Figure 8
A1: This file presents the data from the figures in CBO’s January 2026 report The Distribution of Household Income, 2022.
A2: www.cbo.gov/publication/61911
A5: Figure 8. Income Groups’ Shares of Income Before Transfers and Taxes, 1979 to 2022
A6: Percent
B8: Lowest quintile | C8: Middle three quintiles | D8: 81st to 99th percentiles | E8: Top 1 percent
A9: 1979 | B9: 5 | C9: 49.6 | D9: 36.6 | E9: 9
A10: 1980 | B10: 4.9 | C10: 49.5 | D10: 37 | E10: 9
A11: 1981 | B11: 4.7 | C11: 49.5 | D11: 37.3 | E11: 9
A12: 1982 | B12: 4.4 | C12: 49.2 | D12: 37.5 | E12: 9.5
A13: 1983 | B13: 4.1 | C13: 48.6 | D13: 37.7 | E13: 10.2
A14: 1984 | B14: 4.3 | C14: 48.4 | D14: 37.3 | E14: 10.7
A15: 1985 | B15: 4.1 | C15: 47.8 | D15: 37.4 | E15: 11.3
A16: 1986 | B16: 3.9 | C16: 46 | D16: 36.9 | E16: 13.8
A17: 1987 | B17: 3.7 | C17: 48 | D17: 38 | E17: 11.1
A18: 1988 | B18: 3.7 | C18: 46.7 | D18: 37.2 | E18: 13.2
A19: 1989 | B19: 3.8 | C19: 47 | D19: 37.7 | E19: 12.3
A20: 1990 | B20: 3.9 | C20: 47.3 | D20: 37.6 | E20: 12
... A52: 2022 | B52: 3.7 | C52: 41.4 | D52: 38 | E52: 17.8
A55: Back to Table of Contents

Sheet Figure 9
A1: This file presents the data from the figures in CBO’s January 2026 report The Distribution of Household Income, 2022.
A2: www.cbo.gov/publication/61911
A5: Figure 9. Average Means-Tested Transfer Rates for Selected Income Groups, 1979 to 2022
A6: Percent
E8: Excluding effects of expanded unemployment compensation
B9: Lowest quintile | C9: Second quintile | D9: Middle quintile | E9: Lowest quintile | F9: Second quintile | G9: Middle quintile
A10: 1979 | B10: 32.1 | C10: 2.4 | D10: 0.8
A11: 1980 | B11: 35.7 | C11: 2.8 | D11: 0.8
A12: 1981 | B12: 37.2 | C12: 3.1 | D12: 0.8
A13: 1982 | B13: 40.5 | C13: 2.9 | D13: 0.6
A14: 1983 | B14: 44.8 | C14: 2.8 | D14: 0.7
A15: 1984 | B15: 38.9 | C15: 2.7 | D15: 0.7
A16: 1985 | B16: 41.4 | C16: 2.6 | D16: 0.7
A17: 1986 | B17: 42.2 | C17: 3 | D17: 0.7
A18: 1987 | B18: 46.3 | C18: 2.9 | D18: 0.6
A19: 1988 | B19: 45.2 | C19: 2.8 | D19: 0.7
A20: 1989 | B20: 45.5 | C20: 3 | D20: 0.7
A21: 1990 | B21: 47.4 | C21: 3.5 | D21: 0.9
... A49: 2018 | B49: 70.9 | C49: 14.8 | D49: 4.7
A50: 2019 | B50: 65 | C50: 14.2 | D50: 4.6 | E50: 65 | F50: 14.2 | G50: 4.6
A51: 2020 | B51: 92.5 | C51: 23 | D51: 8.7 | E51: 74.3 | F51: 16.444 | G51: 5.408
A52: 2021 | B52: 88.4 | C52: 20.1 | D52: 7.5 | E52: 77.456 | F52: 16.56 | G52: 5.868
A53: 2022 | B53: 72.3 | C53: 16.2 | D53: 6 | E53: 72.3 | F53: 16.2 | G53: 6
A56: Back to Table of Contents

Sheet Figure 10
A1: This file presents the data from the figures in CBO’s January 2026 report The Distribution of Household Income, 2022.
A2: www.cbo.gov/publication/61911
A5: Figure 10. Average Means-Tested Transfer Rates for Households in the Lowest Quintile, by Type of Transfer, 1979 to 2022
A6: Percent
B8: Medicaid and CHIP | C8: SNAP | D8: SSI | E8: Other transfers | F8: Other transfers, excluding effects of expanded unemployment compensation
A9: 1979 | B9: 9 | C9: 5.9 | D9: 4.7 | E9: 12.5
A10: 1980 | B10: 9.9 | C10: 6.8 | D10: 5.4 | E10: 13.6
A11: 1981 | B11: 10.3 | C11: 7.5 | D11: 5.2 | E11: 14.2
A12: 1982 | B12: 11.3 | C12: 7.7 | D12: 5.5 | E12: 15.9
A13: 1983 | B13: 12.7 | C13: 8.4 | D13: 5.8 | E13: 17.9
A14: 1984 | B14: 11.2 | C14: 6.6 | D14: 5.3 | E14: 15.7
A15: 1985 | B15: 12.3 | C15: 6.8 | D15: 5.5 | E15: 16.9
A16: 1986 | B16: 13.1 | C16: 6.6 | D16: 5.6 | E16: 16.8
A17: 1987 | B17: 15 | C17: 7 | D17: 6.3 | E17: 18
A18: 1988 | B18: 14.9 | C18: 6.7 | D18: 6.2 | E18: 17.3
A19: 1989 | B19: 15.9 | C19: 6.6 | D19: 6 | E19: 17
A20: 1990 | B20: 17.2 | C20: 7.1 | D20: 5.8 | E20: 17.2
... A48: 2018 | B48: 48.4 | C48: 6.9 | D48: 6 | E48: 9.6
A49: 2019 | B49: 45 | C49: 5.8 | D49: 5.2 | E49: 9 | F49: 9
A50: 2020 | B50: 50.8 | C50: 8.6 | D50: 5.4 | E50: 27.7 | F50: 9.5
A51: 2021 | B51: 51.3 | C51: 11.1 | D51: 5.6 | E51: 20.5 | F51: 9.556
A52: 2022 | B52: 48 | C52: 10.1 | D52: 4.8 | E52: 9.4 | F52: 9.4
A55: Back to Table of Contents

Sheet Figure 11
A1: This file presents the data from the figures in CBO’s January 2026 report The Distribution of Household Income, 2022.
A2: www.cbo.gov/publication/61911
A5: Figure 11. Average Federal Tax Rates, 1979 to 2022
A6: Percent
G8: Excluding effects of recovery rebate credits and expanded child tax credit
B9: Lowest quintile | C9: Middle three quintiles | D9: 81st to 99th percentiles | E9: Top 1 percent | G9: Lowest quintile | H9: Middle three quintiles | I9: 81st to 99th percentiles | J9: Top 1 percent
A10: 1979 | B10: 9.3 | C10: 19.3 | D10: 25.1 | E10: 35.1
A11: 1980 | B11: 8.9 | C11: 19.3 | D11: 25.5 | E11: 33.1
A12: 1981 | B12: 9.6 | C12: 19.8 | D12: 25.7 | E12: 30.5
A13: 1982 | B13: 9.8 | C13: 18.4 | D13: 23.5 | E13: 26.8
A14: 1983 | B14: 11.1 | C14: 18 | D14: 22.7 | E14: 26.8
A15: 1984 | B15: 12.1 | C15: 18.4 | D15: 22.9 | E15: 27
A16: 1985 | B16: 11.8 | C16: 18.5 | D16: 23 | E16: 26
A17: 1986 | B17: 11.7 | C17: 18.6 | D17: 23.1 | E17: 24.6
A18: 1987 | B18: 10.7 | C18: 18.3 | D18: 24.3 | E18: 30
A19: 1988 | B19: 10.1 | C19: 18.7 | D19: 24.3 | E19: 28.6
A20: 1989 | B20: 9.6 | C20: 18.6 | D20: 24.1 | E20: 27.9
A21: 1990 | B21: 10.6 | C21: 18.7 | D21: 24.1 | E21: 27.7
... A49: 2018 | B49: -0.2 | C49: 13.8 | D49: 22 | E49: 30.3
A50: 2019 | B50: 0.6 | C50: 13.9 | D50: 22 | E50: 30 | G50: 0.6 | H50: 13.9 | I50: 22 | J50: 30
A51: 2020 | B51: -16.5 | C51: 9 | D51: 21.1 | E51: 30.2 | G51: 0.219 | H51: 13.573 | I51: 22.14 | J51: 30.281
A52: 2021 | B52: -22.5 | C52: 9.2 | D52: 21.9 | E52: 29.8 | G52: -0.235 | H52: 13.787 | I52: 22.633 | J52: 29.859
A53: 2022 | B53: 1.4 | C53: 14.6 | D53: 23.2 | E53: 31.5 | G53: 1.4 | H53: 14.6 | I53: 23.2 | J53: 31.5
A56: Back to Table of Contents

Sheet Figure 12
A1: This file presents the data from the figures in CBO’s January 2026 report The Distribution of Household Income, 2022.
A2: www.cbo.gov/publication/61911
A5: Figure 12. Average Federal Tax Rates for Households in the Top 1 Percent, 1979 to 2022
A6: Percent
B8: 99th to 99.9th percentiles | C8: 99.9th to 99.99th percentiles | D8: Top 0.01 percent
A9: 1979 | B9: 32.9 | C9: 38.3 | D9: 39.7
A10: 1980 | B10: 31.8 | C10: 34.7 | D10: 36.5
A11: 1981 | B11: 30 | C11: 31.5 | D11: 31.2
A12: 1982 | B12: 26.6 | C12: 27.4 | D12: 26.5
A13: 1983 | B13: 25.7 | C13: 28.1 | D13: 29.2
A14: 1984 | B14: 25.8 | C14: 27.9 | D14: 30.1
A15: 1985 | B15: 24.9 | C15: 27.7 | D15: 27.8
A16: 1986 | B16: 24.4 | C16: 24.8 | D16: 24.8
A17: 1987 | B17: 29 | C17: 31.2 | D17: 32.1
A18: 1988 | B18: 27.8 | C18: 28.9 | D18: 30.5
A19: 1989 | B19: 27.3 | C19: 28.1 | D19: 29.6
A20: 1990 | B20: 27 | C20: 28.1 | D20: 29.5
... A52: 2022 | B52: 31 | C52: 32.6 | D52: 31.2
A55: Back to Table of Contents

Sheet Figure 13
A1: This file presents the data from the figures in CBO’s January 2026 report The Distribution of Household Income, 2022.
A2: www.cbo.gov/publication/61911
A5: Figure 13. Average Federal Tax Rates, by Type of Tax, 1979 to 2022
A6: Percent
H8: Excluding effects of recovery rebate credits and expanded child tax credit
B9: All federal taxes | C9: Individual income tax | D9: Payroll taxes | E9: Corporate income tax | F9: Excise taxes | H9: All federal taxes | I9: Individual income tax
A10: 1979 | B10: 22.4 | C10: 11.1 | D10: 6.9 | E10: 3.4 | F10: 1
A11: 1980 | B11: 22.4 | C11: 11.8 | D11: 7 | E11: 2.8 | F11: 0.8
A12: 1981 | B12: 22.6 | C12: 12.1 | D12: 7.5 | E12: 2.2 | F12: 0.8
A13: 1982 | B13: 20.9 | C13: 11.1 | D13: 7.6 | E13: 1.4 | F13: 0.8
A14: 1983 | B14: 20.5 | C14: 10.3 | D14: 7.5 | E14: 1.8 | F14: 0.9
A15: 1984 | B15: 20.9 | C15: 10.1 | D15: 7.7 | E15: 2 | F15: 1
A16: 1985 | B16: 21 | C16: 10.2 | D16: 7.9 | E16: 1.9 | F16: 0.9
A17: 1986 | B17: 21 | C17: 10.4 | D17: 7.8 | E17: 1.9 | F17: 0.9
A18: 1987 | B18: 21.8 | C18: 10.3 | D18: 8.1 | E18: 2.4 | F18: 0.9
A19: 1988 | B19: 21.9 | C19: 10.5 | D19: 8.2 | E19: 2.4 | F19: 0.9
A20: 1989 | B20: 21.6 | C20: 10.3 | D20: 8.2 | E20: 2.3 | F20: 0.8
A21: 1990 | B21: 21.7 | C21: 10.2 | D21: 8.4 | E21: 2.2 | F21: 0.9
... A49: 2018 | B49: 19.4 | C49: 9.4 | D49: 7.8 | E49: 1.6 | F49: 0.6
A50: 2019 | B50: 19.3 | C50: 9.3 | D50: 7.8 | E50: 1.5 | F50: 0.6 | H50: 19.3 | I50: 9.3
A51: 2020 | B51: 16.6 | C51: 6.9 | D51: 7.6 | E51: 1.5 | F51: 0.5 | H51: 19.513 | I51: 9.813
A52: 2021 | B52: 17.4 | C52: 8.3 | D52: 7.1 | E52: 1.6 | F52: 0.4 | H52: 20.2 | I52: 11.1
A53: 2022 | B53: 20.6 | C53: 10.6 | D53: 7.5 | E53: 2.1 | F53: 0.4 | H53: 20.6 | I53: 10.6
A56: Back to Table of Contents

Sheet Figure 14
A1: This file presents the data from the figures in CBO’s January 2026 report The Distribution of Household Income, 2022.
A2: www.cbo.gov/publication/61911
A5: Figure 14. Average Federal Tax Rates, by Type of Tax and Income Group, 1979 to 2022
A6: Percent
B8: Individual income tax | H8: Payroll taxes | L8: Corporate income tax | P8: Excise taxes
E9: Excluding effects of recovery rebate credits and expanded child tax credit
B10: Lowest quintile | C10: Middle three quintiles | D10: Highest quintile | E10: Lowest quintile | F10: Middle three quintiles | H10: Lowest quintile | I10: Middle three quintiles | J10: Highest quintile | L10: Lowest quintile | M10: Middle three quintiles | N10: Highest quintile | P10: Lowest quintile | Q10: Middle three quintiles | R10: Highest quintile
A11: 1979 | B11: -0.2 | C11: 7.9 | D11: 15.9 | H11: 6 | I11: 8.3 | J11: 5.5 | L11: 1.5 | M11: 2.1 | N11: 5 | P11: 1.9 | Q11: 1.1 | R11: 0.7
A12: 1980 | B12: 0 | C12: 8.4 | D12: 16.6 | H12: 6 | I12: 8.3 | J12: 5.6 | L12: 1.2 | M12: 1.7 | N12: 4.1 | P12: 1.7 | Q12: 0.9 | R12: 0.6
A13: 1981 | B13: 0.4 | C13: 8.8 | D13: 16.7 | H13: 6.7 | I13: 8.8 | J13: 6.1 | L13: 1 | M13: 1.4 | N13: 3.2 | P13: 1.5 | Q13: 0.8 | R13: 0.6
A14: 1982 | B14: 0.4 | C14: 7.9 | D14: 15.4 | H14: 7 | I14: 8.7 | J14: 6.3 | L14: 0.7 | M14: 0.9 | N14: 1.9 | P14: 1.7 | Q14: 0.9 | R14: 0.6
A15: 1983 | B15: 0.4 | C15: 7.2 | D15: 14.2 | H15: 7.4 | I15: 8.7 | J15: 6.3 | L15: 0.8 | M15: 1.1 | N15: 2.5 | P15: 2.5 | Q15: 1 | R15: 0.7
A16: 1984 | B16: 0.8 | C16: 7 | D16: 14 | H16: 7.6 | I16: 9 | J16: 6.4 | L16: 1 | M16: 1.3 | N16: 2.8 | P16: 2.6 | Q16: 1.1 | R16: 0.7
A17: 1985 | B17: 0.6 | C17: 7 | D17: 14 | H17: 7.8 | I17: 9.3 | J17: 6.5 | L17: 0.8 | M17: 1.2 | N17: 2.6 | P17: 2.6 | Q17: 1.1 | R17: 0.7
A18: 1986 | B18: 0.4 | C18: 7 | D18: 14.2 | H18: 8 | I18: 9.4 | J18: 6.2 | L18: 0.9 | M18: 1.2 | N18: 2.6 | P18: 2.4 | Q18: 1 | R18: 0.6
A19: 1987 | B19: -0.7 | C19: 6.3 | D19: 14.9 | H19: 7.7 | I19: 9.3 | J19: 6.7 | L19: 1.1 | M19: 1.6 | N19: 3.3 | P19: 2.6 | Q19: 1.1 | R19: 0.7
A20: 1988 | B20: -1.4 | C20: 6.4 | D20: 14.9 | H20: 8 | I20: 9.7 | J20: 6.6 | L20: 1.1 | M20: 1.5 | N20: 3.2 | P20: 2.4 | Q20: 1.1 | R20: 0.6
A21: 1989 | B21: -1.9 | C21: 6.4 | D21: 14.7 | H21: 8.3 | I21: 9.7 | J21: 6.6 | L21: 1 | M21: 1.5 | N21: 3.1 | P21: 2.2 | Q21: 1 | R21: 0.6
A22: 1990 | B22: -1.2 | C22: 6.5 | D22: 14.5 | H22: 8.6 | I22: 9.9 | J22: 6.9 | L22: 1 | M22: 1.4 | N22: 3 | P22: 2.3 | Q22: 1 | R22: 0.6
... A50: 2018 | B50: -12.1 | C50: 3.1 | D50: 15.4 | H50: 9.4 | I50: 9.1 | J50: 6.4 | L50: 0.6 | M50: 0.7 | N50: 2.3 | P50: 1.9 | Q50: 0.8 | R50: 0.4
A51: 2019 | B51: -11.1 | C51: 3.3 | D51: 15.3 | E51: -11.1 | F51: 3.3 | H51: 9.5 | I51: 9.1 | J51: 6.5 | L51: 0.5 | M51: 0.7 | N51: 2.1 | P51: 1.7 | Q51: 0.8 | R51: 0.4
A52: 2020 | B52: -27.4 | C52: -1.2 | D52: 15.2 | E52: -9.1998994 | F52: 3.3725326 | H52: 8.9 | I52: 8.8 | J52: 6.4 | L52: 0.5 | M52: 0.7 | N52: 2.1 | P52: 1.4 | Q52: 0.7 | R52: 0.3
A53: 2021 | B53: -33.3 | C53: -1.1 | D53: 16.7 | E53: -14.796285 | F53: 3.52056 | H53: 8.9 | I53: 8.9 | J53: 5.6 | L53: 0.6 | M53: 0.7 | N53: 2.2 | P53: 1.4 | Q53: 0.6 | R53: 0.3
A54: 2022 | B54: -10.1 | C54: 4 | D54: 16.6 | E54: -10.2 | F54: 4.1 | H54: 9.5 | I54: 9 | J54: 6.1 | L54: 0.8 | M54: 0.9 | N54: 2.9 | P54: 1.4 | Q54: 0.6 | R54: 0.3
A57: Back to Table of Contents

Sheet Figure 15
A1: This file presents the data from the figures in CBO’s January 2026 report The Distribution of Household Income, 2022.
A2: www.cbo.gov/publication/61911
A5: Figure 15. Average Refundable Credits Measured as a Percentage of Income Before Transfers and Taxes for Selected Income Groups, 1979 to 2022
A6: Percent
F8: Excluding effects of recovery rebate credits and expanded child tax credit
B9: Lowest quintile | C9: Second quintile | D9: Middle quintile | F9: Lowest quintile | G9: Second quintile | H9: Middle quintile
A10: 1979 | B10: 1.2 | C10: 0.2 | D10: 0.1
A11: 1980 | B11: 1 | C11: 0.1 | D11: 0
A12: 1981 | B12: 1.1 | C12: 0.1 | D12: 0
A13: 1982 | B13: 0.9 | C13: 0.1 | D13: 0
A14: 1983 | B14: 1 | C14: 0.1 | D14: 0
A15: 1984 | B15: 0.8 | C15: 0.1 | D15: 0
A16: 1985 | B16: 0.9 | C16: 0.1 | D16: 0
A17: 1986 | B17: 0.9 | C17: 0.1 | D17: 0
A18: 1987 | B18: 1.7 | C18: 0.3 | D18: 0.1
A19: 1988 | B19: 2.2 | C19: 0.4 | D19: 0.1
A20: 1989 | B20: 2.8 | C20: 0.8 | D20: 0.2
A21: 1990 | B21: 2.3 | C21: 0.4 | D21: 0.1
... A49: 2018 | B49: 13.3 | C49: 5 | D49: 2.4
A50: 2019 | B50: 12.4 | C50: 4.5 | D50: 2.2 | F50: 12.4 | G50: 4.5 | H50: 2.2
A51: 2020 | B51: 28.6 | C51: 11.8 | D51: 6.9 | F51: 11.952 | G51: 4.369 | H51: 2.085
A52: 2021 | B52: 34.7 | C52: 12.7 | D52: 7.2 | F52: 12.373 | G52: 4.613 | H52: 2.256
A53: 2022 | B53: 11.7 | C53: 4 | D53: 1.9 | F53: 11.7 | G53: 4 | H53: 1.9
A56: Back to Table of Contents

Sheet Figure 16
A1: This file presents the data from the figures in CBO’s January 2026 report The Distribution of Household Income, 2022.
A2: www.cbo.gov/publication/61911
A5: Figure 16. Income Groups’ Shares of Federal Taxes, 1979 to 2022
A6: Percent
B8: Lower three quintiles | C8: Fourth quintile | D8: 81st to 99th percentiles | E8: Top 1 percent
A9: 1979 | B9: 23.2 | C9: 21.6 | D9: 41 | E9: 14.1
A10: 1980 | B10: 22.8 | C10: 21.8 | D10: 42 | E10: 13.2
A11: 1981 | B11: 23.2 | C11: 22.2 | D11: 42.4 | E11: 12.1
A12: 1982 | B12: 23.1 | C12: 22.3 | D12: 42.3 | E12: 12.2
A13: 1983 | B13: 22.8 | C13: 22.1 | D13: 41.7 | E13: 13.3
A14: 1984 | B14: 23.4 | C14: 21.8 | D14: 40.8 | E14: 13.8
A15: 1985 | B15: 23.1 | C15: 21.6 | D15: 41.1 | E15: 14.1
A16: 1986 | B16: 22 | C16: 21 | D16: 40.7 | E16: 16.2
A17: 1987 | B17: 21.1 | C17: 21 | D17: 42.4 | E17: 15.3
A18: 1988 | B18: 20.8 | C18: 20.7 | D18: 41.1 | E18: 17.2
A19: 1989 | B19: 20.9 | C19: 21 | D19: 42 | E19: 15.9
A20: 1990 | B20: 21.7 | C20: 21.1 | D20: 41.7 | E20: 15.4
... A52: 2022 | B52: 12.8 | C52: 16.8 | D52: 42.9 | E52: 27.3
A55: Back to Table of Contents

Sheet Figure 17
A1: This file presents the data from the figures in CBO’s January 2026 report The Distribution of Household Income, 2022.
A2: www.cbo.gov/publication/61911
A5: Figure 17. Average Income After Transfers and Taxes, 2019 to 2022
A6: Thousands of 2022 dollars
B8: 2019 | C8: 2020 | D8: 2021 | E8: 2022
A9: Lowest quintile | B9: 44.123312 | C9: 50.702479 | D9: 51.695085 | E9: 44.838
A10: Second quintile | B10: 62.249531 | C10: 69.97847 | D10: 68.99598 | E10: 63.138
A11: Middle quintile | B11: 84.510173 | C11: 93.400004 | D11: 92.498198 | E11: 86.997
A12: Fourth quintile | B12: 117.88376 | C12: 127.55248 | D12: 125.94489 | E12: 121.052
A13: Highest quintile | B13: 284.40978 | C13: 305.72426 | D13: 337.84279 | E13: 307.649
A16: Back to Table of Contents

Sheet Figure 18
A1: This file presents the data from the figures in CBO’s January 2026 report The Distribution of Household Income, 2022.
A2: www.cbo.gov/publication/61911
A5: Figure 18. Average Income After Transfers and Taxes and Its Growth, 1979 to 2022
B8: Average income (thousands of 2022 dollars) | I8: Cumulative growth (percent)
E9: Excluding effects of recovery rebate credits, expanded unemployment compensation, and expanded child tax credit | L9: Excluding effects of recovery rebate credits, expanded unemployment compensation, and expanded child tax credit
B10: Lowest quintile | C10: Middle three quintiles | D10: Highest quintile | E10: Lowest quintile | F10: Middle three quintiles | G10: Highest quintile | I10: Lowest quintile | J10: Middle three quintiles | K10: Highest quintile | L10: Lowest quintile | M10: Middle three quintiles
A11: 1979 | B11: 22.4 | C11: 54.7 | D11: 126.3 | I11: 0 | J11: 0 | K11: 0
A12: 1980 | B12: 22.2 | C12: 53 | D12: 123.2 | I12: -1 | J12: -3 | K12: -2
A13: 1981 | B13: 22.1 | C13: 52.8 | D13: 123.3 | I13: -1 | J13: -4 | K13: -2
A14: 1982 | B14: 21.9 | C14: 52.9 | D14: 128.3 | I14: -2 | J14: -3 | K14: 2
A15: 1983 | B15: 21.4 | C15: 52.6 | D15: 133.9 | I15: -5 | J15: -4 | K15: 6
A16: 1984 | B16: 21.8 | C16: 55.3 | D16: 144.9 | I16: -3 | J16: 1 | K16: 15
A17: 1985 | B17: 22.2 | C17: 55.3 | D17: 146.8 | I17: -1 | J17: 1 | K17: 16
A18: 1986 | B18: 22.1 | C18: 56.7 | D18: 165.2 | I18: -1 | J18: 4 | K18: 31
A19: 1987 | B19: 22.1 | C19: 56.5 | D19: 152.1 | I19: -2 | J19: 3 | K19: 20
A20: 1988 | B20: 22.8 | C20: 57 | D20: 163.3 | I20: 2 | J20: 4 | K20: 29
A21: 1989 | B21: 24 | C21: 57.6 | D21: 163.5 | I21: 7 | J21: 5 | K21: 29
A22: 1990 | B22: 24.9 | C22: 58.1 | D22: 159.8 | I22: 11 | J22: 6 | K22: 27
... A50: 2018 | B50: 42.5 | C50: 84.7 | D50: 278.4 | I50: 90 | J50: 55 | K50: 120
A51: 2019 | B51: 44.1 | C51: 88.1 | D51: 284.4 | E51: 44.1 | F51: 88.1 | G51: 284.4 | I51: 97 | J51: 61 | K51: 125 | L51: 97 | M51: 61
A52: 2020 | B52: 50.7 | C52: 96.6 | D52: 305.7 | E52: 42.236 | F52: 89.083 | G52: 300.97 | I52: 126 | J52: 76 | K52: 142 | L52: 89 | M52: 63
A53: 2021 | B53: 51.7 | C53: 95.5 | D53: 337.8 | E53: 43.552 | F53: 89.487 | G53: 334.925 | I53: 131 | J53: 74 | K53: 168 | L53: 94 | M53: 64
A54: 2022 | B54: 44.8 | C54: 90.1 | D54: 307.6 | E54: 44.8 | F54: 90.1 | G54: 307.6 | I54: 100 | J54: 65 | K54: 144 | L54: 100 | M54: 65
A57: Back to Table of Contents

Sheet Figure 19
A1: This file presents the data from the figures in CBO’s January 2026 report The Distribution of Household Income, 2022.
A2: www.cbo.gov/publication/61911
A5: Figure 19. Cumulative Growth in Average Income After Transfers and Taxes for Households in the Highest Quintile, 1979 to 2022
A6: Percent
B8: 81st to 99th percentiles | C8: 99th to 99.9th percentiles | D8: 99.9th to 99.99th percentiles | E8: Top 0.01 percent
A9: 1979 | B9: 0 | C9: 0 | D9: 0 | E9: 0
A10: 1980 | B10: -3 | C10: -1 | D10: 8 | E10: -7
A11: 1981 | B11: -3 | C11: 0 | D11: 11 | E11: -1
A12: 1982 | B12: -1 | C12: 6 | D12: 31 | E12: 38
A13: 1983 | B13: 2 | C13: 17 | D13: 46 | E13: 36
A14: 1984 | B14: 10 | C14: 26 | D14: 63 | E14: 63
A15: 1985 | B15: 9 | C15: 37 | D15: 73 | E15: 80
A16: 1986 | B16: 16 | C16: 64 | D16: 184 | E16: 205
A17: 1987 | B17: 15 | C17: 39 | D17: 75 | E17: 60
A18: 1988 | B18: 17 | C18: 62 | D18: 135 | E18: 142
A19: 1989 | B19: 20 | C19: 58 | D19: 113 | E19: 115
A20: 1990 | B20: 18 | C20: 55 | D20: 105 | E20: 104
... A52: 2022 | B52: 108 | C52: 230 | D52: 492 | E52: 628
A55: Back to Table of Contents

Sheet Figure 20
A1: This file presents the data from the figures in CBO’s January 2026 report The Distribution of Household Income, 2022.
A2: www.cbo.gov/publication/61911
A5: Figure 20. Income Groups’ Shares of Income After Transfers and Taxes, 1979 to 2022
A6: Percent
B8: Lowest quintile | C8: Middle three quintiles | D8: 81st to 99th percentiles | E8: Top 1 percent
A9: 1979 | B9: 7.8 | C9: 50.8 | D9: 34.4 | E9: 7.4
A10: 1980 | B10: 7.8 | C10: 50.6 | D10: 34.6 | E10: 7.5
A11: 1981 | B11: 7.6 | C11: 50.4 | D11: 34.7 | E11: 7.8
A12: 1982 | B12: 7.1 | C12: 49.8 | D12: 35.2 | E12: 8.5
A13: 1983 | B13: 6.7 | C13: 49.3 | D13: 35.6 | E13: 9.1
A14: 1984 | B14: 6.8 | C14: 49.1 | D14: 35.4 | E14: 9.6
A15: 1985 | B15: 6.6 | C15: 48.4 | D15: 35.5 | E15: 10.3
A16: 1986 | B16: 6.2 | C16: 46.7 | D16: 35 | E16: 12.8
A17: 1987 | B17: 6.2 | C17: 49.3 | D17: 35.8 | E17: 9.7
A18: 1988 | B18: 6.2 | C18: 47.9 | D18: 35.2 | E18: 11.7
A19: 1989 | B19: 6.3 | C19: 48 | D19: 35.5 | E19: 11
A20: 1990 | B20: 6.7 | C20: 48.2 | D20: 35.4 | E20: 10.7
... A52: 2022 | B52: 7.4 | C52: 44.6 | D52: 34.6 | E52: 14.4
A55: Back to Table of Contents

Sheet Figure 21
A1: This file presents the data from the figures in CBO’s January 2026 report The Distribution of Household Income, 2022.
A2: www.cbo.gov/publication/61911
A5: Figure 21. Income Inequality, as Measured by the Gini Coefficient, 1979 to 2022
A6: Gini coefficient
B8: Market income | C8: Income before transfers and taxes | D8: Income after transfers but before taxes | E8: Income after transfers and taxes | F8: Income after transfers and taxes, excluding effects of recovery rebate credits, expanded unemployment compensation, and expanded child tax credit
A9: 1979 | B9: 0.472 | C9: 0.412 | D9: 0.391 | E9: 0.352
A10: 1980 | B10: 0.48 | C10: 0.416 | D10: 0.393 | E10: 0.354
A11: 1981 | B11: 0.484 | C11: 0.419 | D11: 0.396 | E11: 0.361
A12: 1982 | B12: 0.493 | C12: 0.425 | D12: 0.402 | E12: 0.373
A13: 1983 | B13: 0.505 | C13: 0.438 | D13: 0.414 | E13: 0.387
A14: 1984 | B14: 0.505 | C14: 0.443 | D14: 0.42 | E14: 0.395
A15: 1985 | B15: 0.511 | C15: 0.448 | D15: 0.425 | E15: 0.401
A16: 1986 | B16: 0.534 | C16: 0.471 | D16: 0.448 | E16: 0.425
A17: 1987 | B17: 0.519 | C17: 0.455 | D17: 0.432 | E17: 0.401
A18: 1988 | B18: 0.532 | C18: 0.469 | D18: 0.446 | E18: 0.416
A19: 1989 | B19: 0.525 | C19: 0.462 | D19: 0.439 | E19: 0.41
A20: 1990 | B20: 0.52 | C20: 0.455 | D20: 0.43 | E20: 0.403
... A48: 2018 | B48: 0.601 | C48: 0.524 | D48: 0.48 | E48: 0.438
A49: 2019 | B49: 0.59 | C49: 0.514 | D49: 0.471 | E49: 0.43 | F49: 0.43
A50: 2020 | B50: 0.62 | C50: 0.534 | D50: 0.475 | E50: 0.417 | F50: 0.446
A51: 2021 | B51: 0.635 | C51: 0.557 | D51: 0.504 | E51: 0.442 | F51: 0.467
A52: 2022 | B52: 0.604 | C52: 0.525 | D52: 0.479 | E52: 0.434 | F52: 0.434
A55: Back to Table of Contents

Sheet Figure 22
A1: This file presents the data from the figures in CBO’s January 2026 report The Distribution of Household Income, 2022.
A2: www.cbo.gov/publication/61911
A5: Figure 22. Reduction in Income Inequality Stemming From Means-Tested Transfers and Federal Taxes, 1979 to 2022
A6: Change in Gini coefficient
A8: 1979 | B8: -0.06
A9: 1980 | B9: -0.062
A10: 1981 | B10: -0.058
A11: 1982 | B11: -0.052
A12: 1983 | B12: -0.051
A13: 1984 | B13: -0.048
A14: 1985 | B14: -0.047
A15: 1986 | B15: -0.046
A16: 1987 | B16: -0.054
A17: 1988 | B17: -0.053
A18: 1989 | B18: -0.052
A19: 1990 | B19: -0.052
... A47: 2018 | B47: -0.086
A48: 2019 | B48: -0.084 | C48: -0.084
A49: 2020 | B49: -0.117 | C49: -0.088
A50: 2021 | B50: -0.115 | C50: -0.09
A51: 2022 | B51: -0.091 | C51: -0.092
A54: Back to Table of Contents
